adafruit_blinka_raspberry_pi5_piomatter/__init__.py
adafruit_blinka_raspberry_pi5_piomatter/_piomatter.cpython-313-aarch64-linux-gnu.so
adafruit_blinka_raspberry_pi5_piomatter/click.py
adafruit_blinka_raspberry_pi5_piomatter/pixelmappers.py
adafruit_blinka_raspberry_pi5_piomatter-1.0.0.dist-info/METADATA
adafruit_blinka_raspberry_pi5_piomatter-1.0.0.dist-info/WHEEL
adafruit_blinka_raspberry_pi5_piomatter-1.0.0.dist-info/top_level.txt
adafruit_blinka_raspberry_pi5_piomatter-1.0.0.dist-info/RECORD
adafruit_blinka_raspberry_pi5_piomatter-1.0.0.dist-info/licenses/LICENSE
