Metadata-Version: 2.4
Name: Adafruit-Blinka-Raspberry-Pi5-Piomatter
Version: 1.0.0
Summary: HUB75 matrix driver for Raspberry Pi 5 using PIO
Home-page: https://github.com/adafruit/Adafruit_Blinka_Raspberry_Pi5_Piomatter
Requires-Python: >=3.11
License-File: LICENSE
Provides-Extra: docs
Requires-Dist: sphinx; extra == "docs"
Requires-Dist: sphinx-rtd-theme; extra == "docs"
Requires-Dist: sphinxcontrib-jquery; extra == "docs"
Dynamic: description
Dynamic: home-page
Dynamic: license-file
Dynamic: provides-extra
Dynamic: requires-python
Dynamic: summary
